{
  "users": [
    {
      "id": 1,
      "name": "Leanne Graham",
      "nickname": "Bret",
      "email": "Sincere@april.biz",
      "token": "f0478b1441b5509761fb56447e97c6f8bd2ac760c01fb0408c6b5c51830a5bd9"
    },
    {
      "id": 2,
      "name": "김민설",
      "nickname": "민설",
      "email": "blessoms2017@gmail.com",
      "token": "cf6df401ace708235fe27c54e224762a3e2a63d6470fbb2a94517e6530f0d60e"
    },
    {
      "name": "미미",
      "nickname": "미미",
      "email": "ansdkf@naver.com",
      "token": "asndfkdslafn123125nskzndfksnb",
      "id": 3
    }
  ],
  "post": [
    {
      "id": 1,
      "title": "처음 공지사항",
      "content": "첫 번째 공지사항입니다.",
      "author": "관리자",
      "day": "2022.06.12"
    }
  ],
  "dashboard": [
    {
      "id": 1,
      "title": "그냥써봤습니다.",
      "token": "q41s5dwe708235fe27c54e156210a3e2a63d6470fbb2a94517e6530f0d60e",
      "content": "안녕하세요"
    },
    {
      "title": "dsdf",
      "content": "<p>sdfsdf</p>",
      "token": "21e62532d429d0f0a31b0cad9f74f59f9feeea8d6960da4a9e28ac5d312e7c55",
      "id": 2
    }
  ]
}